dda_py/__init__.py
dda_py/cli.py
dda_py/dda.py
dda_py/generated.py
dda_py/model_encoding.py
dda_py/runner.py
dda_py/variants.py
dda_py-0.2.7.dist-info/METADATA
dda_py-0.2.7.dist-info/WHEEL
dda_py-0.2.7.dist-info/entry_points.txt
dda_py-0.2.7.dist-info/licenses/LICENSE
dda_py-0.2.7.dist-info/RECORD
