Metadata-Version: 2.4
Name: dda-py
Version: 0.2.7
Summary: Python bindings for DDA (Delay Differential Analysis)
Project-URL: Homepage, https://github.com/sdraeger/dda-py
Project-URL: Repository, https://github.com/sdraeger/dda-py
Project-URL: Issues, https://github.com/sdraeger/dda-py/issues
Author-email: Simon Draeger <sdraeger@salk.edu>
License-Expression: MIT
License-File: LICENSE
Keywords: dda,delay-differential-analysis,neuroscience,signal-processing
Classifier: Development Status :: 4 - Beta
Classifier: Intended Audience :: Science/Research
Classifier: License :: OSI Approved :: MIT License
Classifier: Operating System :: OS Independent
Classifier: Programming Language :: Python :: 3
Classifier: Programming Language :: Python :: 3.8
Classifier: Programming Language :: Python :: 3.9
Classifier: Programming Language :: Python :: 3.10
Classifier: Programming Language :: Python :: 3.11
Classifier: Programming Language :: Python :: 3.12
Classifier: Topic :: Scientific/Engineering
Requires-Python: >=3.8
Provides-Extra: dev
Requires-Dist: numpy>=1.20; extra == 'dev'
Requires-Dist: pytest-cov>=4.0; extra == 'dev'
Requires-Dist: pytest>=7.0; extra == 'dev'
